[
    {
        "name": "editInvitation",
        "outputType": "Invitation",
        "inputType": "Invitation",
        "method": "PUT",
        "placeholder":[{"name":"userid","regex":"%^([0-9_]+)$%"},{"name":"esid","regex":"%^([0-9_]+)$%"},{"name":"memberid","regex":"%^([0-9_]+)$%"}],
        "path": "/invitation/user/:userid/exercisesheet/:esid/user/:memberid"
    },
    {
        "name": "deleteInvitation",
        "outputType": "Invitation",
        "inputType": "",
        "method": "DELETE",
        "placeholder":[{"name":"userid","regex":"%^([0-9_]+)$%"},{"name":"esid","regex":"%^([0-9_]+)$%"},{"name":"memberid","regex":"%^([0-9_]+)$%"}],
        "path": "/invitation/user/:userid/exercisesheet/:esid/user/:memberid"
    },
    {
        "name": "addInvitation",
        "outputType": "Invitation",
        "inputType": "Invitation",
        "method": "POST",
        "path": "/invitation"
    },
    {
        "name": "getLeaderInvitations",
        "callback": "getMatch",
        "outputType": "Invitation",
        "inputType": "",
        "method": "GET",
        "placeholder":[{"name":"userid","regex":"%^([0-9_]+)$%"}],
        "path": "/invitation/leader/user/:userid"
    },
    {
        "name": "getMemberInvitations",
        "callback": "getMatch",
        "outputType": "Invitation",
        "inputType": "",
        "method": "GET",
        "placeholder":[{"name":"userid","regex":"%^([0-9_]+)$%"}],
        "path": "/invitation/member/user/:userid"
    },
    {
        "name": "getAllInvitations",
        "callback": "getMatch",
        "outputType": "Invitation",
        "inputType": "",
        "method": "GET",
        "path": "/invitation"
    },
    {
        "name": "getSheetLeaderInvitations",
        "callback": "getMatch",
        "outputType": "Invitation",
        "inputType": "",
        "method": "GET",
        "placeholder":[{"name":"esid","regex":"%^([0-9_]+)$%"},{"name":"userid","regex":"%^([0-9_]+)$%"}],
        "path": "/invitation/leader/exercisesheet/:esid/user/:userid"
    },
    {
        "name": "getSheetMemberInvitations",
        "callback": "getMatch",
        "outputType": "Invitation",
        "inputType": "",
        "method": "GET",
        "placeholder":[{"name":"esid","regex":"%^([0-9_]+)$%"},{"name":"userid","regex":"%^([0-9_]+)$%"}],
        "path": "/invitation/member/exercisesheet/:esid/user/:userid"
    },
    {
        "name": "getSheetInvitations",
        "callback": "getMatch",
        "outputType": "Invitation",
        "inputType": "",
        "method": "GET",
        "placeholder":[{"name":"esid","regex":"%^([0-9_]+)$%"}],
        "path": "/invitation/exercisesheet/:esid"
    },
    {
        "name": "addPlatform",
        "outputType": "Platform",
        "inputType": "Platform",
        "method": "POST",
        "path": "/platform"
    },
    {
        "name": "deletePlatform",
        "outputType": "Platform",
        "inputType": "",
        "method": "DELETE",
        "path": "/platform"
    },
    {
        "name": "getExistsPlatform",
        "callback": "getMatch",
        "singleOutput": "TRUE",
        "outputType": "Platform",
        "inputType": "",
        "method": "GET",
        "path": "/link/exists/platform"
    }
]