[
    {
        "__commentFile": "@file AttachmentSample.json This file represents a valid JSON object of type Attachment for DBAttachment.",
        "__commentAuthor": "@author Till Uhlig"
    },
    {
        "id": "1",
        "exerciseId": "1",
        "file": {
            "fileId": "1",
            "displayName": "a.pdf",
            "address": "file/abcdef",
            "timeStamp": "1389643115",
            "fileSize": "100",
            "hash": "abcdef"
        }
    },
    {
        "id": "2",
        "exerciseId": "2",
        "file": {
            "fileId": "2",
            "displayName": "b.pdf",
            "address": "file/abcde",
            "timeStamp": "1389643115",
            "fileSize": "200",
            "hash": "abcde"
        }
    },
    {
        "id": "3",
        "exerciseId": "3",
        "file": {
            "fileId": "3",
            "displayName": "c.pdf",
            "address": "file/abcd",
            "timeStamp": "1389643115",
            "fileSize": "300",
            "hash": "abcd"
        }
    },
    {
        "id": "4",
        "exerciseId": "4",
        "file": {
            "fileId": "4",
            "displayName": "d.pdf",
            "address": "file/abc",
            "timeStamp": "1389643115",
            "fileSize": "400",
            "hash": "abc"
        }
    },
    {
        "id": "5",
        "exerciseId": "1",
        "file": {
            "fileId": "5",
            "displayName": "e.pdf",
            "address": "file/ab",
            "timeStamp": "1389643115",
            "fileSize": "500",
            "hash": "ab"
        }
    }
]