[
    {
        "name": "getExistsPlatform",
        "path": "\/link\/exists\/platform",
        "method": "GET",
        "description": {
            "de": "pr\\u00fcft, ob die Tabelle und die Prozeduren existieren und die Komponente generell vollst\u00e4ndig installiert ist"
        },
        "inputType": "",
        "outputType": "Platform",
        "callback": "getMatch",
        "singleOutput": "TRUE"
    },
    {
        "name": "deleteExercise",
        "path": "\/exercise\/exercise\/:eid",
        "method": "DELETE",
        "description": {
            "de": "entfernt eine Aufgabe"
        },
        "placeholder": [
            {
                "name": "eid",
                "regex": "%^([0-9_]+)$%",
                "description": {
                    "de": "die ID einer Aufgabe (`Exercise`)"
                }
            }
        ],
        "inputType": "",
        "outputType": "Exercise"
    },
    {
        "name": "editExercise",
        "path": "\/exercise\/exercise\/:eid",
        "method": "PUT",
        "description": {
            "de": "editiert eine Aufgabe"
        },
        "placeholder": [
            {
                "name": "eid",
                "regex": "%^([0-9_]+)$%",
                "description": {
                    "de": "die ID einer Aufgabe (`Exercise`)"
                }
            }
        ],
        "inputType": "Exercise",
        "outputType": "Exercise"
    },
    {
        "name": "getExercise",
        "path": "\/exercise\/exercise\/:eid(\/:sub)",
        "method": "GET",
        "description": {
            "de": "liefert eine einzelne Aufgabe (sub=nosubmission bedeutet ohne Einsendungen)"
        },
        "placeholder": [
            {
                "name": "eid",
                "regex": "%^([0-9_]+)$%",
                "description": {
                    "de": "die ID einer Aufgabe (`Exercise`)"
                }
            }
        ],
        "inputType": "",
        "outputType": "Exercise",
        "callback": "getMatch",
        "singleOutput": "TRUE"
    },
    {
        "name": "getAllExercises",
        "path": "\/exercise(\/:sub)",
        "method": "GET",
        "description": {
            "de": "liefert alle Aufgaben (sub=nosubmission bedeutet ohne Einsendungen)"
        },
        "inputType": "",
        "outputType": "Exercise",
        "callback": "getMatch"
    },
    {
        "name": "postSamples",
        "path": "\/samples\/course\/:courseAmount\/user\/:userAmount",
        "method": "POST",
        "description": {
            "de": "erzeugt Zufallsdaten (courseAmount = Anzahl der Veranstaltungen, userAmount = Anzahl der Nutzer), anhand der Vorgabe"
        },
        "inputType": "",
        "outputType": "Query"
    },
    {
        "name": "getSheetExercises",
        "path": "\/exercise\/exercisesheet\/:esid(\/:sub)",
        "method": "GET",
        "description": {
            "de": "liefert die Aufgaben einer \u00dcbungsserie (sub=nosubmission bedeutet ohne Einsendungen)"
        },
        "placeholder": [
            {
                "name": "esid",
                "regex": "%^([0-9_]+)$%",
                "description": {
                    "de": "die ID einer \u00dcbungsserie (`ExerciseSheet`)"
                }
            }
        ],
        "inputType": "",
        "outputType": "Exercise",
        "callback": "getMatch"
    },
    {
        "name": "getCourseExercises",
        "path": "\/exercise\/course\/:courseid(\/:sub)",
        "method": "GET",
        "description": {
            "de": "liefert die Aufgaben einer Veranstaltung (sub=nosubmission bedeutet ohne Einsendungen)"
        },
        "placeholder": [
            {
                "name": "courseid",
                "regex": "%^([0-9_]+)$%",
                "description": {
                    "de": "eine Veranstaltungs ID (`Course`)"
                }
            }
        ],
        "inputType": "",
        "outputType": "Exercise",
        "callback": "getMatch"
    },
    {
        "name": "deletePlatform",
        "path": "\/platform",
        "method": "DELETE",
        "description": {
            "de": "entfernt die Komponente und ihre installierten Bestandteile aus der Plattform"
        },
        "inputType": "",
        "outputType": "Platform"
    },
    {
        "name": "addExercise",
        "path": "\/exercise",
        "method": "POST",
        "description": {
            "de": "f\u00fcgt eine Aufgabe ein"
        },
        "inputType": "Exercise",
        "outputType": "Exercise"
    },
    {
        "name": "getSamplesInfo",
        "path": "\/samples",
        "method": "GET",
        "description": {
            "de": "liefert die Bezeichner der betroffenen Tabellen"
        },
        "inputType": "",
        "outputType": ""
    },
    {
        "name": "addPlatform",
        "path": "\/platform",
        "method": "POST",
        "description": {
            "de": "installiert dies zugeh\\u00f6rige Tabelle und die Prozeduren f\\u00fcr diese Plattform"
        },
        "inputType": "Platform",
        "outputType": "Platform"
    },
    {
        "name": "getApiProfiles",
        "path": "\/api\/profiles",
        "method": "GET",
        "description": {
            "de": "liefert `GateProfile`-Objekte, welche unsere Befehle in die Standardprofile von CGate einsortieren"
        },
        "inputType": "",
        "outputType": "GateProfile"
    }
]